packages/__init__.py
packages/kian.py
packages/shaan.py
shanthapkg-1.1.1.dist-info/LICENSE
shanthapkg-1.1.1.dist-info/METADATA
shanthapkg-1.1.1.dist-info/WHEEL
shanthapkg-1.1.1.dist-info/top_level.txt
shanthapkg-1.1.1.dist-info/RECORD
