Metadata-Version: 2.1
Name: shanthapkg
Version: 1.1.1
Summary: A brief description of my package.
Author: vishwa
Author-email: vishwa.automationhub@gmail.com
Requires-Python: >=3.8
License-File: LICENSE
Requires-Dist: numpy>=1.20.0
Requires-Dist: pandas>=1.3.5
